mccole/__init__.py
mccole/build.py
mccole/check.py
mccole/clui.py
mccole/create.py
mccole/util.py
mccole/data/CODE_OF_CONDUCT.md
mccole/data/CONTRIBUTING.md
mccole/data/LICENSE.md
mccole/data/Makefile
mccole/data/README.md
mccole/data/pyproject.toml
mccole/data/bibliography/index.md
mccole/data/extras/links.md
mccole/data/glossary/index.md
mccole/data/static/favicon.ico
mccole/data/static/page.css
mccole/data/static/shower.js
mccole/data/static/slides.css
mccole/data/templates/page.html
mccole/data/templates/slides.html
mccole-1.4.3.dist-info/METADATA
mccole-1.4.3.dist-info/WHEEL
mccole-1.4.3.dist-info/entry_points.txt
mccole-1.4.3.dist-info/licenses/LICENSE.md
mccole-1.4.3.dist-info/RECORD
